sah/__init__.py
sah/_version.py
sah/classes.py
sah/deuterium.py
sah/fit.py
sah/normalize.py
sah/plot.py
sah/samples.py
sah-2.0.0a6.dist-info/licenses/LICENSE
tests/__init__.py
tests/test_ins.py
tests/test_material.py
tests/test_raman.py
sah-2.0.0a6.dist-info/METADATA
sah-2.0.0a6.dist-info/WHEEL
sah-2.0.0a6.dist-info/top_level.txt
sah-2.0.0a6.dist-info/RECORD
