Metadata-Version: 2.4
Name: sah
Version: 2.0.0a6
Summary: The Spectra Analyser for Hydrogenous samples, or SAH, provides comprehensive tools to analyse INS, FTIR and Raman spectra.
Author: Pablo Gila-Herranz
Author-email: pgila001@ikasle.ehu.eus
License: AGPL-3.0
Keywords: Neutron,Research,Science,Spectra,Inelastic Neutron Scattering,INS,Raman,FTIR,Infrared
Classifier: Development Status :: 5 - Production/Stable
Classifier: Natural Language :: English
Classifier: Intended Audience :: Science/Research
Classifier: Programming Language :: Python :: 3
Classifier: Operating System :: POSIX :: Linux
Classifier: Operating System :: Microsoft :: Windows
Classifier: Operating System :: Other OS
Requires-Python: >=3
License-File: LICENSE
Requires-Dist: scipy
Requires-Dist: numpy
Requires-Dist: pandas
Requires-Dist: matplotlib
Requires-Dist: aton
Dynamic: author
Dynamic: author-email
Dynamic: classifier
Dynamic: description
Dynamic: description-content-type
Dynamic: keywords
Dynamic: license
Dynamic: license-file
Dynamic: requires-dist
Dynamic: requires-python
Dynamic: summary
